{
  "alias": "Nginx",
  "group": "Passerelles",
  "layer-header": {
    "columns": [
      {
        "label": "RPS"
      },
      {
        "label": "5xx %"
      },
      {
        "label": "4xx %"
      }
    ]
  },
  "dashboards": {
    "service": [
      {
        "title": "Tendance des requêtes HTTP"
      },
      {
        "title": "Latence HTTP"
      },
      {
        "title": "Bande passante HTTP"
      },
      {
        "title": "Connexions HTTP"
      },
      {
        "title": "Tendance des statuts HTTP"
      },
      {
        "title": "4xx % / min"
      },
      {
        "title": "5xx % / min"
      },
      {
        "title": "Nombre de logs d'erreur"
      }
    ],
    "instance": [
      {
        "title": "Tendance des requêtes HTTP"
      },
      {
        "title": "Latence HTTP"
      },
      {
        "title": "Bande passante HTTP"
      },
      {
        "title": "Connexions HTTP"
      },
      {
        "title": "Tendance des statuts HTTP"
      },
      {
        "title": "4xx % / min"
      },
      {
        "title": "5xx % / min"
      },
      {
        "title": "Nombre de logs d'erreur"
      }
    ],
    "endpoint": [
      {
        "title": "Tendance des requêtes HTTP"
      },
      {
        "title": "Latence HTTP"
      },
      {
        "title": "Bande passante HTTP"
      },
      {
        "title": "Tendance des statuts HTTP"
      },
      {
        "title": "4xx % / min"
      },
      {
        "title": "5xx % / min"
      }
    ]
  },
  "slots": {
    "services": "Services Nginx",
    "instances": "Nœuds",
    "endpoints": "Routes"
  }
}
